ahui626_test/__init__.py
ahui626_test-0.1.dist-info/METADATA
ahui626_test-0.1.dist-info/WHEEL
ahui626_test-0.1.dist-info/top_level.txt
ahui626_test-0.1.dist-info/RECORD
