Metadata-Version: 2.1
Name: ahui626-test
Version: 0.1
Summary: A simple example package
Home-page: UNKNOWN
Author: ahui
Author-email: your.email@example.com
License: UNKNOWN
Platform: UNKNOWN
Classifier: Programming Language :: Python :: 3
Classifier: License :: OSI Approved :: MIT License
Classifier: Operating System :: OS Independent
Requires-Python: >=3.6
Requires-Dist: requests
